{"map":{"chunks":[[[{"value":0,"type":null},{"value":0,"type":null},{"value":0,"type":null},{"value":0,"type":null},{"value":0,"type":null},{"value":0,"type":null},{"value":0,"type":null},{"value":0,"type":null},{"value":0,"type":null},{"value":0,"type":null},{"value":0,"type":null},{"value":0,"type":null},{"value":0,"type":null},{"value":0,"type":null},{"value":0,"type":null},{"value":0,"type":null},{"value":0,"type":null},{"value":0,"type":null},{"value":0,"type":null},{"value":0,"type":null},{"value":0,"type":null},{"value":0,"type":null},{"value":0,"type":null},{"value":0,"type":null},{"value":0,"type":null},{"value":0,"type":null},{"value":0,"type":null},{"value":0,"type":null},{"value":0,"type":null},{"value":0,"type":null},{"value":0,"type":null},{"value":0,"type":null},{"value":0,"type":null}],[{"value":0,"type":null},{"value":0,"type":null},{"value":0,"type":null},{"value":0,"type":null},{"value":0,"type":null},{"value":0,"type":null},{"value":0,"type":null},{"value":0,"type":null},{"value":0,"type":null},{"value":0,"type":null},{"value":0,"type":null},{"value":0,"type":null},{"value":0,"type":null},{"value":0,"type":null},{"value":0,"type":null},{"value":0,"type":null},{"value":0,"type":null},{"value":0,"type":null},{"value":0,"type":null},{"value":0,"type":null},{"value":0,"type":null},{"value":0,"type":null},{"value":0,"type":null},{"value":0,"type":null},{"value":0,"type":null},{"value":0,"type":null},{"value":0,"type":null},{"value":0,"type":null},{"value":0,"type":null},{"value":0,"type":null},{"value":0,"type":null},{"value":0,"type":null},{"value":0,"type":null}],[{"value":2,"type":"obst"},{"value":2,"type":"obst"},{"value":2,"type":"obst"},{"value":2,"type":"obst"},{"value":17,"type":"ladder"},{"value":2,"type":"obst"},{"value":2,"type":"obst"},{"value":0,"type":null},{"value":0,"type":null},{"value":0,"type":null},{"value":0,"type":null},{"value":0,"type":null},{"value":0,"type":null},{"value":0,"type":null},{"value":0,"type":null},{"value":0,"type":null},{"value":0,"type":null},{"value":0,"type":null},{"value":0,"type":null},{"value":0,"type":null},{"value":0,"type":null},{"value":0,"type":null},{"value":0,"type":null},{"value":0,"type":null},{"value":0,"type":null},{"value":0,"type":null},{"value":0,"type":null},{"value":0,"type":null},{"value":0,"type":null},{"value":0,"type":null},{"value":0,"type":null},{"value":0,"type":null},{"value":0,"type":null}],[{"value":0,"type":null},{"value":0,"type":null},{"value":0,"type":null},{"value":0,"type":null},{"value":17,"type":"ladder"},{"value":0,"type":null},{"value":0,"type":null},{"value":0,"type":null},{"value":0,"type":null},{"value":0,"type":null},{"value":2,"type":"obst"},{"value":2,"type":"obst"},{"value":2,"type":"obst"},{"value":0,"type":null},{"value":0,"type":null},{"value":0,"type":null},{"value":0,"type":null},{"value":0,"type":null},{"value":0,"type":null},{"value":0,"type":null},{"value":0,"type":null},{"value":0,"type":null},{"value":0,"type":null},{"value":0,"type":null},{"value":0,"type":null},{"value":0,"type":null},{"value":0,"type":null},{"value":0,"type":null},{"value":0,"type":null},{"value":0,"type":null},{"value":0,"type":null},{"value":0,"type":null},{"value":0,"type":null}],[{"value":0,"type":null},{"value":0,"type":null},{"value":0,"type":null},{"value":0,"type":null},{"value":17,"type":"ladder"},{"value":0,"type":null},{"value":0,"type":null},{"value":0,"type":null},{"value":0,"type":null},{"value":0,"type":null},{"value":0,"type":null},{"value":0,"type":null},{"value":0,"type":null},{"value":0,"type":null},{"value":0,"type":null},{"value":0,"type":null},{"value":0,"type":null},{"value":0,"type":null},{"value":0,"type":null},{"value":0,"type":null},{"value":0,"type":null},{"value":0,"type":null},{"value":0,"type":null},{"value":0,"type":null},{"value":0,"type":null},{"value":0,"type":null},{"value":0,"type":null},{"value":0,"type":null},{"value":0,"type":null},{"value":0,"type":null},{"value":0,"type":null},{"value":0,"type":null},{"value":0,"type":null}],[{"value":0,"type":null},{"value":0,"type":null},{"value":0,"type":null},{"value":0,"type":null},{"value":17,"type":"ladder"},{"value":0,"type":null},{"value":2,"type":"obst"},{"value":2,"type":"obst"},{"value":2,"type":"obst"},{"value":0,"type":null},{"value":0,"type":null},{"value":0,"type":null},{"value":0,"type":null},{"value":0,"type":null},{"value":0,"type":null},{"value":0,"type":null},{"value":0,"type":null},{"value":0,"type":null},{"value":0,"type":null},{"value":0,"type":null},{"value":0,"type":null},{"value":0,"type":null},{"value":0,"type":null},{"value":0,"type":null},{"value":0,"type":null},{"value":0,"type":null},{"value":0,"type":null},{"value":0,"type":null},{"value":0,"type":null},{"value":0,"type":null},{"value":0,"type":null},{"value":0,"type":null},{"value":0,"type":null}],[{"value":0,"type":null},{"value":0,"type":null},{"value":0,"type":null},{"value":0,"type":null},{"value":17,"type":"ladder"},{"value":0,"type":null},{"value":0,"type":null},{"value":0,"type":null},{"value":0,"type":null},{"value":0,"type":null},{"value":0,"type":null},{"value":0,"type":null},{"value":0,"type":null},{"value":0,"type":null},{"value":0,"type":null},{"value":0,"type":null},{"value":0,"type":null},{"value":0,"type":null},{"value":0,"type":null},{"value":0,"type":null},{"value":0,"type":null},{"value":0,"type":null},{"value":0,"type":null},{"value":0,"type":null},{"value":0,"type":null},{"value":0,"type":null},{"value":0,"type":null},{"value":0,"type":null},{"value":0,"type":null},{"value":0,"type":null},{"value":0,"type":null},{"value":0,"type":null},{"value":0,"type":null}],[{"value":0,"type":null},{"value":0,"type":null},{"value":0,"type":null},{"value":0,"type":null},{"value":17,"type":"ladder"},{"value":0,"type":null},{"value":0,"type":null},{"value":0,"type":null},{"value":0,"type":null},{"value":2,"type":"obst"},{"value":2,"type":"obst"},{"value":2,"type":"obst"},{"value":2,"type":"obst"},{"value":2,"type":"obst"},{"value":0,"type":null},{"value":0,"type":null},{"value":0,"type":null},{"value":0,"type":null},{"value":0,"type":null},{"value":0,"type":null},{"value":0,"type":null},{"value":0,"type":null},{"value":0,"type":null},{"value":0,"type":null},{"value":0,"type":null},{"value":0,"type":null},{"value":0,"type":null},{"value":0,"type":null},{"value":0,"type":null},{"value":0,"type":null},{"value":0,"type":null},{"value":0,"type":null},{"value":0,"type":null}],[{"value":2,"type":"obst"},{"value":2,"type":"obst"},{"value":2,"type":"obst"},{"value":2,"type":"obst"},{"value":2,"type":"obst"},{"value":2,"type":"obst"},{"value":2,"type":"obst"},{"value":2,"type":"obst"},{"value":0,"type":null},{"value":0,"type":null},{"value":0,"type":null},{"value":0,"type":null},{"value":0,"type":null},{"value":0,"type":null},{"value":0,"type":null},{"value":0,"type":null},{"value":0,"type":null},{"value":0,"type":null},{"value":0,"type":null},{"value":0,"type":null},{"value":0,"type":null},{"value":0,"type":null},{"value":0,"type":null},{"value":0,"type":null},{"value":0,"type":null},{"value":0,"type":null},{"value":0,"type":null},{"value":0,"type":null},{"value":0,"type":null},{"value":0,"type":null},{"value":0,"type":null},{"value":0,"type":null},{"value":0,"type":null}],[{"value":0,"type":null},{"value":0,"type":null},{"value":0,"type":null},{"value":0,"type":null},{"value":0,"type":null},{"value":0,"type":null},{"value":0,"type":null},{"value":0,"type":null},{"value":0,"type":null},{"value":0,"type":null},{"value":0,"type":null},{"value":0,"type":null},{"value":0,"type":null},{"value":0,"type":null},{"value":0,"type":null},{"value":0,"type":null},{"value":0,"type":null},{"value":0,"type":null},{"value":0,"type":null},{"value":0,"type":null},{"value":0,"type":null},{"value":0,"type":null},{"value":0,"type":null},{"value":0,"type":null},{"value":0,"type":null},{"value":0,"type":null},{"value":0,"type":null},{"value":0,"type":null},{"value":0,"type":null},{"value":0,"type":null},{"value":0,"type":null},{"value":0,"type":null},{"value":0,"type":null}],[{"value":0,"type":null},{"value":0,"type":null},{"value":0,"type":null},{"value":0,"type":null},{"value":0,"type":null},{"value":0,"type":null},{"value":0,"type":null},{"value":0,"type":null},{"value":0,"type":null},{"value":0,"type":null},{"value":0,"type":null},{"value":0,"type":null},{"value":0,"type":null},{"value":0,"type":null},{"value":0,"type":null},{"value":0,"type":null},{"value":0,"type":null},{"value":0,"type":null},{"value":0,"type":null},{"value":0,"type":null},{"value":0,"type":null},{"value":0,"type":null},{"value":0,"type":null},{"value":0,"type":null},{"value":0,"type":null},{"value":0,"type":null},{"value":0,"type":null},{"value":0,"type":null},{"value":0,"type":null},{"value":0,"type":null},{"value":0,"type":null},{"value":0,"type":null},{"value":0,"type":null}],[{"value":0,"type":null},{"value":0,"type":null},{"value":0,"type":null},{"value":0,"type":null},{"value":0,"type":null},{"value":0,"type":null},{"value":0,"type":null},{"value":0,"type":null},{"value":0,"type":null},{"value":0,"type":null},{"value":0,"type":null},{"value":0,"type":null},{"value":0,"type":null},{"value":0,"type":null},{"value":0,"type":null},{"value":0,"type":null},{"value":0,"type":null},{"value":0,"type":null},{"value":0,"type":null},{"value":0,"type":null},{"value":0,"type":null},{"value":0,"type":null},{"value":0,"type":null},{"value":0,"type":null},{"value":0,"type":null},{"value":0,"type":null},{"value":0,"type":null},{"value":0,"type":null},{"value":0,"type":null},{"value":0,"type":null},{"value":0,"type":null},{"value":0,"type":null},{"value":0,"type":null}],[{"value":0,"type":null},{"value":0,"type":null},{"value":0,"type":null},{"value":0,"type":null},{"value":0,"type":null},{"value":0,"type":null},{"value":0,"type":null},{"value":0,"type":null},{"value":0,"type":null},{"value":0,"type":null},{"value":0,"type":null},{"value":0,"type":null},{"value":0,"type":null},{"value":0,"type":null},{"value":0,"type":null},{"value":0,"type":null},{"value":0,"type":null},{"value":0,"type":null},{"value":0,"type":null},{"value":0,"type":null},{"value":0,"type":null},{"value":0,"type":null},{"value":0,"type":null},{"value":0,"type":null},{"value":0,"type":null},{"value":0,"type":null},{"value":0,"type":null},{"value":0,"type":null},{"value":0,"type":null},{"value":0,"type":null},{"value":0,"type":null},{"value":0,"type":null},{"value":0,"type":null}],[{"value":0,"type":null},{"value":0,"type":null},{"value":0,"type":null},{"value":0,"type":null},{"value":0,"type":null},{"value":0,"type":null},{"value":0,"type":null},{"value":0,"type":null},{"value":0,"type":null},{"value":0,"type":null},{"value":0,"type":null},{"value":0,"type":null},{"value":0,"type":null},{"value":0,"type":null},{"value":0,"type":null},{"value":0,"type":null},{"value":0,"type":null},{"value":0,"type":null},{"value":0,"type":null},{"value":0,"type":null},{"value":0,"type":null},{"value":0,"type":null},{"value":0,"type":null},{"value":0,"type":null},{"value":0,"type":null},{"value":0,"type":null},{"value":0,"type":null},{"value":0,"type":null},{"value":0,"type":null},{"value":0,"type":null},{"value":0,"type":null},{"value":0,"type":null},{"value":0,"type":null}],[{"value":0,"type":null},{"value":0,"type":null},{"value":0,"type":null},{"value":0,"type":null},{"value":0,"type":null},{"value":0,"type":null},{"value":0,"type":null},{"value":0,"type":null},{"value":0,"type":null},{"value":0,"type":null},{"value":0,"type":null},{"value":0,"type":null},{"value":0,"type":null},{"value":0,"type":null},{"value":0,"type":null},{"value":0,"type":null},{"value":0,"type":null},{"value":0,"type":null},{"value":0,"type":null},{"value":0,"type":null},{"value":0,"type":null},{"value":0,"type":null},{"value":0,"type":null},{"value":0,"type":null},{"value":0,"type":null},{"value":0,"type":null},{"value":0,"type":null},{"value":0,"type":null},{"value":0,"type":null},{"value":0,"type":null},{"value":0,"type":null},{"value":0,"type":null},{"value":0,"type":null}],[{"value":0,"type":null},{"value":0,"type":null},{"value":0,"type":null},{"value":0,"type":null},{"value":0,"type":null},{"value":0,"type":null},{"value":0,"type":null},{"value":0,"type":null},{"value":0,"type":null},{"value":0,"type":null},{"value":0,"type":null},{"value":0,"type":null},{"value":0,"type":null},{"value":0,"type":null},{"value":0,"type":null},{"value":0,"type":null},{"value":0,"type":null},{"value":0,"type":null},{"value":0,"type":null},{"value":0,"type":null},{"value":0,"type":null},{"value":0,"type":null},{"value":0,"type":null},{"value":0,"type":null},{"value":0,"type":null},{"value":0,"type":null},{"value":0,"type":null},{"value":0,"type":null},{"value":0,"type":null},{"value":0,"type":null},{"value":0,"type":null},{"value":0,"type":null},{"value":0,"type":null}],[{"value":0,"type":null},{"value":0,"type":null},{"value":0,"type":null},{"value":0,"type":null},{"value":0,"type":null},{"value":0,"type":null},{"value":0,"type":null},{"value":0,"type":null},{"value":0,"type":null},{"value":0,"type":null},{"value":0,"type":null},{"value":0,"type":null},{"value":0,"type":null},{"value":0,"type":null},{"value":0,"type":null},{"value":0,"type":null},{"value":0,"type":null},{"value":0,"type":null},{"value":0,"type":null},{"value":0,"type":null},{"value":0,"type":null},{"value":0,"type":null},{"value":0,"type":null},{"value":0,"type":null},{"value":0,"type":null},{"value":0,"type":null},{"value":0,"type":null},{"value":0,"type":null},{"value":0,"type":null},{"value":0,"type":null},{"value":0,"type":null},{"value":0,"type":null},{"value":0,"type":null}],[{"value":0,"type":null},{"value":0,"type":null},{"value":0,"type":null},{"value":0,"type":null},{"value":0,"type":null},{"value":0,"type":null},{"value":0,"type":null},{"value":0,"type":null},{"value":0,"type":null},{"value":0,"type":null},{"value":0,"type":null},{"value":0,"type":null},{"value":0,"type":null},{"value":0,"type":null},{"value":0,"type":null},{"value":0,"type":null},{"value":0,"type":null},{"value":0,"type":null},{"value":0,"type":null},{"value":0,"type":null},{"value":0,"type":null},{"value":0,"type":null},{"value":0,"type":null},{"value":0,"type":null},{"value":0,"type":null},{"value":0,"type":null},{"value":0,"type":null},{"value":0,"type":null},{"value":0,"type":null},{"value":0,"type":null},{"value":0,"type":null},{"value":0,"type":null},{"value":0,"type":null}],[{"value":0,"type":null},{"value":0,"type":null},{"value":0,"type":null},{"value":0,"type":null},{"value":0,"type":null},{"value":0,"type":null},{"value":0,"type":null},{"value":0,"type":null},{"value":0,"type":null},{"value":0,"type":null},{"value":0,"type":null},{"value":0,"type":null},{"value":0,"type":null},{"value":0,"type":null},{"value":0,"type":null},{"value":0,"type":null},{"value":0,"type":null},{"value":0,"type":null},{"value":0,"type":null},{"value":0,"type":null},{"value":0,"type":null},{"value":0,"type":null},{"value":0,"type":null},{"value":0,"type":null},{"value":0,"type":null},{"value":0,"type":null},{"value":0,"type":null},{"value":0,"type":null},{"value":0,"type":null},{"value":0,"type":null},{"value":0,"type":null},{"value":0,"type":null},{"value":0,"type":null}],[{"value":0,"type":null},{"value":0,"type":null},{"value":0,"type":null},{"value":0,"type":null},{"value":0,"type":null},{"value":0,"type":null},{"value":0,"type":null},{"value":0,"type":null},{"value":0,"type":null},{"value":0,"type":null},{"value":0,"type":null},{"value":0,"type":null},{"value":0,"type":null},{"value":0,"type":null},{"value":0,"type":null},{"value":0,"type":null},{"value":0,"type":null},{"value":0,"type":null},{"value":0,"type":null},{"value":0,"type":null},{"value":0,"type":null},{"value":0,"type":null},{"value":0,"type":null},{"value":0,"type":null},{"value":0,"type":null},{"value":0,"type":null},{"value":0,"type":null},{"value":0,"type":null},{"value":0,"type":null},{"value":0,"type":null},{"value":0,"type":null},{"value":0,"type":null},{"value":0,"type":null}]],[[{"value":0,"type":null},{"value":0,"type":null},{"value":0,"type":null},{"value":0,"type":null},{"value":0,"type":null},{"value":0,"type":null},{"value":0,"type":null},{"value":0,"type":null},{"value":0,"type":null},{"value":0,"type":null},{"value":0,"type":null},{"value":0,"type":null},{"value":0,"type":null},{"value":0,"type":null},{"value":0,"type":null},{"value":0,"type":null},{"value":0,"type":null},{"value":0,"type":null},{"value":0,"type":null},{"value":0,"type":null},{"value":0,"type":null},{"value":0,"type":null},{"value":0,"type":null},{"value":0,"type":null},{"value":0,"type":null},{"value":0,"type":null},{"value":0,"type":null},{"value":0,"type":null},{"value":0,"type":null},{"value":0,"type":null},{"value":0,"type":null},{"value":0,"type":null},{"value":0,"type":null}],[{"value":0,"type":null},{"value":0,"type":null},{"value":0,"type":null},{"value":0,"type":null},{"value":0,"type":null},{"value":0,"type":null},{"value":0,"type":null},{"value":0,"type":null},{"value":0,"type":null},{"value":0,"type":null},{"value":0,"type":null},{"value":0,"type":null},{"value":0,"type":null},{"value":0,"type":null},{"value":0,"type":null},{"value":0,"type":null},{"value":0,"type":null},{"value":0,"type":null},{"value":0,"type":null},{"value":0,"type":null},{"value":0,"type":null},{"value":0,"type":null},{"value":0,"type":null},{"value":0,"type":null},{"value":0,"type":null},{"value":0,"type":null},{"value":0,"type":null},{"value":0,"type":null},{"value":0,"type":null},{"value":0,"type":null},{"value":0,"type":null},{"value":0,"type":null},{"value":0,"type":null}],[{"value":0,"type":null},{"value":0,"type":null},{"value":0,"type":null},{"value":0,"type":null},{"value":0,"type":null},{"value":0,"type":null},{"value":0,"type":null},{"value":0,"type":null},{"value":0,"type":null},{"value":0,"type":null},{"value":0,"type":null},{"value":0,"type":null},{"value":0,"type":null},{"value":0,"type":null},{"value":0,"type":null},{"value":0,"type":null},{"value":0,"type":null},{"value":0,"type":null},{"value":0,"type":null},{"value":0,"type":null},{"value":0,"type":null},{"value":0,"type":null},{"value":0,"type":null},{"value":0,"type":null},{"value":0,"type":null},{"value":0,"type":null},{"value":0,"type":null},{"value":0,"type":null},{"value":0,"type":null},{"value":0,"type":null},{"value":0,"type":null},{"value":0,"type":null},{"value":0,"type":null}],[{"value":0,"type":null},{"value":0,"type":null},{"value":0,"type":null},{"value":0,"type":null},{"value":0,"type":null},{"value":0,"type":null},{"value":0,"type":null},{"value":0,"type":null},{"value":0,"type":null},{"value":0,"type":null},{"value":0,"type":null},{"value":0,"type":null},{"value":0,"type":null},{"value":0,"type":null},{"value":0,"type":null},{"value":0,"type":null},{"value":0,"type":null},{"value":0,"type":null},{"value":0,"type":null},{"value":0,"type":null},{"value":0,"type":null},{"value":0,"type":null},{"value":0,"type":null},{"value":0,"type":null},{"value":0,"type":null},{"value":0,"type":null},{"value":0,"type":null},{"value":0,"type":null},{"value":0,"type":null},{"value":0,"type":null},{"value":0,"type":null},{"value":0,"type":null},{"value":0,"type":null}],[{"value":0,"type":null},{"value":0,"type":null},{"value":0,"type":null},{"value":0,"type":null},{"value":0,"type":null},{"value":0,"type":null},{"value":0,"type":null},{"value":0,"type":null},{"value":0,"type":null},{"value":0,"type":null},{"value":0,"type":null},{"value":0,"type":null},{"value":0,"type":null},{"value":0,"type":null},{"value":0,"type":null},{"value":0,"type":null},{"value":0,"type":null},{"value":0,"type":null},{"value":0,"type":null},{"value":0,"type":null},{"value":0,"type":null},{"value":0,"type":null},{"value":0,"type":null},{"value":0,"type":null},{"value":0,"type":null},{"value":0,"type":null},{"value":0,"type":null},{"value":0,"type":null},{"value":0,"type":null},{"value":0,"type":null},{"value":0,"type":null},{"value":0,"type":null},{"value":0,"type":null}],[{"value":0,"type":null},{"value":0,"type":null},{"value":0,"type":null},{"value":0,"type":null},{"value":0,"type":null},{"value":0,"type":null},{"value":0,"type":null},{"value":0,"type":null},{"value":0,"type":null},{"value":0,"type":null},{"value":0,"type":null},{"value":0,"type":null},{"value":0,"type":null},{"value":0,"type":null},{"value":0,"type":null},{"value":0,"type":null},{"value":0,"type":null},{"value":0,"type":null},{"value":0,"type":null},{"value":0,"type":null},{"value":0,"type":null},{"value":0,"type":null},{"value":0,"type":null},{"value":0,"type":null},{"value":0,"type":null},{"value":0,"type":null},{"value":0,"type":null},{"value":0,"type":null},{"value":0,"type":null},{"value":0,"type":null},{"value":0,"type":null},{"value":0,"type":null},{"value":0,"type":null}],[{"value":0,"type":null},{"value":0,"type":null},{"value":0,"type":null},{"value":0,"type":null},{"value":0,"type":null},{"value":0,"type":null},{"value":0,"type":null},{"value":0,"type":null},{"value":0,"type":null},{"value":0,"type":null},{"value":0,"type":null},{"value":0,"type":null},{"value":0,"type":null},{"value":0,"type":null},{"value":0,"type":null},{"value":0,"type":null},{"value":0,"type":null},{"value":0,"type":null},{"value":0,"type":null},{"value":0,"type":null},{"value":0,"type":null},{"value":0,"type":null},{"value":0,"type":null},{"value":0,"type":null},{"value":0,"type":null},{"value":0,"type":null},{"value":0,"type":null},{"value":0,"type":null},{"value":0,"type":null},{"value":0,"type":null},{"value":0,"type":null},{"value":0,"type":null},{"value":0,"type":null}],[{"value":0,"type":null},{"value":0,"type":null},{"value":0,"type":null},{"value":0,"type":null},{"value":0,"type":null},{"value":0,"type":null},{"value":0,"type":null},{"value":0,"type":null},{"value":0,"type":null},{"value":0,"type":null},{"value":0,"type":null},{"value":0,"type":null},{"value":0,"type":null},{"value":0,"type":null},{"value":0,"type":null},{"value":0,"type":null},{"value":0,"type":null},{"value":0,"type":null},{"value":0,"type":null},{"value":0,"type":null},{"value":0,"type":null},{"value":0,"type":null},{"value":0,"type":null},{"value":0,"type":null},{"value":0,"type":null},{"value":0,"type":null},{"value":0,"type":null},{"value":0,"type":null},{"value":0,"type":null},{"value":0,"type":null},{"value":0,"type":null},{"value":0,"type":null},{"value":0,"type":null}],[{"value":0,"type":null},{"value":0,"type":null},{"value":0,"type":null},{"value":0,"type":null},{"value":0,"type":null},{"value":0,"type":null},{"value":0,"type":null},{"value":0,"type":null},{"value":0,"type":null},{"value":0,"type":null},{"value":0,"type":null},{"value":0,"type":null},{"value":0,"type":null},{"value":0,"type":null},{"value":0,"type":null},{"value":0,"type":null},{"value":0,"type":null},{"value":0,"type":null},{"value":0,"type":null},{"value":0,"type":null},{"value":0,"type":null},{"value":0,"type":null},{"value":0,"type":null},{"value":0,"type":null},{"value":0,"type":null},{"value":0,"type":null},{"value":0,"type":null},{"value":0,"type":null},{"value":0,"type":null},{"value":0,"type":null},{"value":0,"type":null},{"value":0,"type":null},{"value":0,"type":null}],[{"value":0,"type":null},{"value":0,"type":null},{"value":0,"type":null},{"value":0,"type":null},{"value":0,"type":null},{"value":0,"type":null},{"value":0,"type":null},{"value":0,"type":null},{"value":0,"type":null},{"value":0,"type":null},{"value":0,"type":null},{"value":0,"type":null},{"value":0,"type":null},{"value":0,"type":null},{"value":0,"type":null},{"value":0,"type":null},{"value":0,"type":null},{"value":0,"type":null},{"value":0,"type":null},{"value":0,"type":null},{"value":0,"type":null},{"value":0,"type":null},{"value":0,"type":null},{"value":0,"type":null},{"value":0,"type":null},{"value":0,"type":null},{"value":0,"type":null},{"value":0,"type":null},{"value":0,"type":null},{"value":0,"type":null},{"value":0,"type":null},{"value":0,"type":null},{"value":0,"type":null}],[{"value":0,"type":null},{"value":0,"type":null},{"value":0,"type":null},{"value":0,"type":null},{"value":0,"type":null},{"value":0,"type":null},{"value":0,"type":null},{"value":0,"type":null},{"value":0,"type":null},{"value":0,"type":null},{"value":0,"type":null},{"value":0,"type":null},{"value":0,"type":null},{"value":0,"type":null},{"value":0,"type":null},{"value":0,"type":null},{"value":0,"type":null},{"value":0,"type":null},{"value":0,"type":null},{"value":0,"type":null},{"value":0,"type":null},{"value":0,"type":null},{"value":0,"type":null},{"value":0,"type":null},{"value":0,"type":null},{"value":0,"type":null},{"value":0,"type":null},{"value":0,"type":null},{"value":0,"type":null},{"value":0,"type":null},{"value":0,"type":null},{"value":0,"type":null},{"value":0,"type":null}],[{"value":0,"type":null},{"value":0,"type":null},{"value":0,"type":null},{"value":0,"type":null},{"value":0,"type":null},{"value":0,"type":null},{"value":0,"type":null},{"value":0,"type":null},{"value":0,"type":null},{"value":0,"type":null},{"value":0,"type":null},{"value":0,"type":null},{"value":0,"type":null},{"value":0,"type":null},{"value":0,"type":null},{"value":0,"type":null},{"value":0,"type":null},{"value":0,"type":null},{"value":0,"type":null},{"value":0,"type":null},{"value":0,"type":null},{"value":0,"type":null},{"value":0,"type":null},{"value":0,"type":null},{"value":0,"type":null},{"value":0,"type":null},{"value":0,"type":null},{"value":0,"type":null},{"value":0,"type":null},{"value":0,"type":null},{"value":0,"type":null},{"value":0,"type":null},{"value":0,"type":null}],[{"value":0,"type":null},{"value":0,"type":null},{"value":0,"type":null},{"value":0,"type":null},{"value":0,"type":null},{"value":0,"type":null},{"value":0,"type":null},{"value":0,"type":null},{"value":0,"type":null},{"value":0,"type":null},{"value":0,"type":null},{"value":0,"type":null},{"value":0,"type":null},{"value":0,"type":null},{"value":0,"type":null},{"value":0,"type":null},{"value":0,"type":null},{"value":0,"type":null},{"value":0,"type":null},{"value":0,"type":null},{"value":0,"type":null},{"value":0,"type":null},{"value":0,"type":null},{"value":0,"type":null},{"value":0,"type":null},{"value":0,"type":null},{"value":0,"type":null},{"value":0,"type":null},{"value":0,"type":null},{"value":0,"type":null},{"value":0,"type":null},{"value":0,"type":null},{"value":0,"type":null}],[{"value":0,"type":null},{"value":0,"type":null},{"value":0,"type":null},{"value":0,"type":null},{"value":0,"type":null},{"value":0,"type":null},{"value":0,"type":null},{"value":0,"type":null},{"value":0,"type":null},{"value":0,"type":null},{"value":0,"type":null},{"value":0,"type":null},{"value":0,"type":null},{"value":0,"type":null},{"value":0,"type":null},{"value":0,"type":null},{"value":0,"type":null},{"value":0,"type":null},{"value":0,"type":null},{"value":0,"type":null},{"value":0,"type":null},{"value":0,"type":null},{"value":0,"type":null},{"value":0,"type":null},{"value":0,"type":null},{"value":0,"type":null},{"value":0,"type":null},{"value":0,"type":null},{"value":0,"type":null},{"value":0,"type":null},{"value":0,"type":null},{"value":0,"type":null},{"value":0,"type":null}],[{"value":0,"type":null},{"value":0,"type":null},{"value":0,"type":null},{"value":0,"type":null},{"value":0,"type":null},{"value":0,"type":null},{"value":0,"type":null},{"value":0,"type":null},{"value":0,"type":null},{"value":0,"type":null},{"value":0,"type":null},{"value":0,"type":null},{"value":0,"type":null},{"value":0,"type":null},{"value":0,"type":null},{"value":0,"type":null},{"value":0,"type":null},{"value":0,"type":null},{"value":0,"type":null},{"value":0,"type":null},{"value":0,"type":null},{"value":0,"type":null},{"value":0,"type":null},{"value":0,"type":null},{"value":0,"type":null},{"value":0,"type":null},{"value":0,"type":null},{"value":0,"type":null},{"value":0,"type":null},{"value":0,"type":null},{"value":0,"type":null},{"value":0,"type":null},{"value":0,"type":null}],[{"value":0,"type":null},{"value":0,"type":null},{"value":0,"type":null},{"value":0,"type":null},{"value":0,"type":null},{"value":0,"type":null},{"value":0,"type":null},{"value":0,"type":null},{"value":0,"type":null},{"value":0,"type":null},{"value":0,"type":null},{"value":0,"type":null},{"value":0,"type":null},{"value":0,"type":null},{"value":0,"type":null},{"value":0,"type":null},{"value":0,"type":null},{"value":0,"type":null},{"value":0,"type":null},{"value":0,"type":null},{"value":0,"type":null},{"value":0,"type":null},{"value":0,"type":null},{"value":0,"type":null},{"value":0,"type":null},{"value":0,"type":null},{"value":0,"type":null},{"value":0,"type":null},{"value":0,"type":null},{"value":0,"type":null},{"value":0,"type":null},{"value":0,"type":null},{"value":0,"type":null}],[{"value":0,"type":null},{"value":0,"type":null},{"value":0,"type":null},{"value":0,"type":null},{"value":0,"type":null},{"value":0,"type":null},{"value":0,"type":null},{"value":0,"type":null},{"value":0,"type":null},{"value":0,"type":null},{"value":0,"type":null},{"value":0,"type":null},{"value":0,"type":null},{"value":0,"type":null},{"value":0,"type":null},{"value":0,"type":null},{"value":0,"type":null},{"value":0,"type":null},{"value":0,"type":null},{"value":0,"type":null},{"value":0,"type":null},{"value":0,"type":null},{"value":0,"type":null},{"value":0,"type":null},{"value":0,"type":null},{"value":0,"type":null},{"value":0,"type":null},{"value":0,"type":null},{"value":0,"type":null},{"value":0,"type":null},{"value":0,"type":null},{"value":0,"type":null},{"value":0,"type":null}],[{"value":0,"type":null},{"value":0,"type":null},{"value":0,"type":null},{"value":0,"type":null},{"value":0,"type":null},{"value":0,"type":null},{"value":0,"type":null},{"value":0,"type":null},{"value":0,"type":null},{"value":0,"type":null},{"value":0,"type":null},{"value":0,"type":null},{"value":0,"type":null},{"value":0,"type":null},{"value":0,"type":null},{"value":0,"type":null},{"value":0,"type":null},{"value":0,"type":null},{"value":0,"type":null},{"value":0,"type":null},{"value":0,"type":null},{"value":0,"type":null},{"value":0,"type":null},{"value":0,"type":null},{"value":0,"type":null},{"value":0,"type":null},{"value":0,"type":null},{"value":0,"type":null},{"value":0,"type":null},{"value":0,"type":null},{"value":0,"type":null},{"value":0,"type":null},{"value":0,"type":null}],[{"value":0,"type":null},{"value":0,"type":null},{"value":0,"type":null},{"value":0,"type":null},{"value":0,"type":null},{"value":0,"type":null},{"value":0,"type":null},{"value":0,"type":null},{"value":0,"type":null},{"value":0,"type":null},{"value":0,"type":null},{"value":0,"type":null},{"value":0,"type":null},{"value":0,"type":null},{"value":0,"type":null},{"value":0,"type":null},{"value":0,"type":null},{"value":0,"type":null},{"value":0,"type":null},{"value":0,"type":null},{"value":0,"type":null},{"value":0,"type":null},{"value":0,"type":null},{"value":0,"type":null},{"value":0,"type":null},{"value":0,"type":null},{"value":0,"type":null},{"value":0,"type":null},{"value":0,"type":null},{"value":0,"type":null},{"value":0,"type":null},{"value":0,"type":null},{"value":0,"type":null}],[{"value":0,"type":null},{"value":0,"type":null},{"value":0,"type":null},{"value":0,"type":null},{"value":0,"type":null},{"value":0,"type":null},{"value":0,"type":null},{"value":0,"type":null},{"value":0,"type":null},{"value":0,"type":null},{"value":0,"type":null},{"value":0,"type":null},{"value":0,"type":null},{"value":0,"type":null},{"value":0,"type":null},{"value":0,"type":null},{"value":0,"type":null},{"value":0,"type":null},{"value":0,"type":null},{"value":0,"type":null},{"value":0,"type":null},{"value":0,"type":null},{"value":0,"type":null},{"value":0,"type":null},{"value":0,"type":null},{"value":0,"type":null},{"value":0,"type":null},{"value":0,"type":null},{"value":0,"type":null},{"value":0,"type":null},{"value":0,"type":null},{"value":0,"type":null},{"value":0,"type":null}]],[[{"value":0,"type":null},{"value":0,"type":null},{"value":0,"type":null},{"value":0,"type":null},{"value":0,"type":null},{"value":0,"type":null},{"value":0,"type":null},{"value":0,"type":null},{"value":0,"type":null},{"value":0,"type":null},{"value":0,"type":null},{"value":0,"type":null},{"value":0,"type":null},{"value":0,"type":null},{"value":0,"type":null},{"value":0,"type":null},{"value":0,"type":null},{"value":0,"type":null},{"value":0,"type":null},{"value":0,"type":null},{"value":0,"type":null},{"value":0,"type":null},{"value":0,"type":null},{"value":0,"type":null},{"value":0,"type":null},{"value":0,"type":null},{"value":0,"type":null},{"value":0,"type":null},{"value":0,"type":null},{"value":0,"type":null},{"value":0,"type":null},{"value":0,"type":null},{"value":0,"type":null}],[{"value":0,"type":null},{"value":0,"type":null},{"value":0,"type":null},{"value":0,"type":null},{"value":0,"type":null},{"value":0,"type":null},{"value":0,"type":null},{"value":0,"type":null},{"value":0,"type":null},{"value":0,"type":null},{"value":0,"type":null},{"value":0,"type":null},{"value":0,"type":null},{"value":0,"type":null},{"value":0,"type":null},{"value":0,"type":null},{"value":0,"type":null},{"value":0,"type":null},{"value":0,"type":null},{"value":0,"type":null},{"value":0,"type":null},{"value":0,"type":null},{"value":0,"type":null},{"value":0,"type":null},{"value":0,"type":null},{"value":0,"type":null},{"value":0,"type":null},{"value":0,"type":null},{"value":0,"type":null},{"value":0,"type":null},{"value":0,"type":null},{"value":0,"type":null},{"value":0,"type":null}],[{"value":0,"type":null},{"value":0,"type":null},{"value":0,"type":null},{"value":0,"type":null},{"value":0,"type":null},{"value":0,"type":null},{"value":0,"type":null},{"value":0,"type":null},{"value":0,"type":null},{"value":0,"type":null},{"value":0,"type":null},{"value":0,"type":null},{"value":0,"type":null},{"value":0,"type":null},{"value":0,"type":null},{"value":0,"type":null},{"value":0,"type":null},{"value":0,"type":null},{"value":0,"type":null},{"value":0,"type":null},{"value":0,"type":null},{"value":0,"type":null},{"value":0,"type":null},{"value":0,"type":null},{"value":0,"type":null},{"value":0,"type":null},{"value":0,"type":null},{"value":0,"type":null},{"value":0,"type":null},{"value":0,"type":null},{"value":0,"type":null},{"value":0,"type":null},{"value":0,"type":null}],[{"value":0,"type":null},{"value":0,"type":null},{"value":0,"type":null},{"value":0,"type":null},{"value":0,"type":null},{"value":0,"type":null},{"value":0,"type":null},{"value":0,"type":null},{"value":0,"type":null},{"value":0,"type":null},{"value":0,"type":null},{"value":0,"type":null},{"value":0,"type":null},{"value":0,"type":null},{"value":0,"type":null},{"value":0,"type":null},{"value":0,"type":null},{"value":0,"type":null},{"value":0,"type":null},{"value":0,"type":null},{"value":0,"type":null},{"value":0,"type":null},{"value":0,"type":null},{"value":0,"type":null},{"value":0,"type":null},{"value":0,"type":null},{"value":0,"type":null},{"value":0,"type":null},{"value":0,"type":null},{"value":0,"type":null},{"value":0,"type":null},{"value":0,"type":null},{"value":0,"type":null}],[{"value":0,"type":null},{"value":0,"type":null},{"value":0,"type":null},{"value":0,"type":null},{"value":0,"type":null},{"value":0,"type":null},{"value":0,"type":null},{"value":0,"type":null},{"value":0,"type":null},{"value":0,"type":null},{"value":0,"type":null},{"value":0,"type":null},{"value":0,"type":null},{"value":0,"type":null},{"value":0,"type":null},{"value":0,"type":null},{"value":0,"type":null},{"value":0,"type":null},{"value":0,"type":null},{"value":0,"type":null},{"value":0,"type":null},{"value":0,"type":null},{"value":0,"type":null},{"value":0,"type":null},{"value":0,"type":null},{"value":0,"type":null},{"value":0,"type":null},{"value":0,"type":null},{"value":0,"type":null},{"value":0,"type":null},{"value":0,"type":null},{"value":0,"type":null},{"value":0,"type":null}],[{"value":0,"type":null},{"value":0,"type":null},{"value":0,"type":null},{"value":0,"type":null},{"value":0,"type":null},{"value":0,"type":null},{"value":0,"type":null},{"value":0,"type":null},{"value":0,"type":null},{"value":0,"type":null},{"value":0,"type":null},{"value":0,"type":null},{"value":0,"type":null},{"value":0,"type":null},{"value":0,"type":null},{"value":0,"type":null},{"value":0,"type":null},{"value":0,"type":null},{"value":0,"type":null},{"value":0,"type":null},{"value":0,"type":null},{"value":0,"type":null},{"value":0,"type":null},{"value":0,"type":null},{"value":0,"type":null},{"value":0,"type":null},{"value":0,"type":null},{"value":0,"type":null},{"value":0,"type":null},{"value":0,"type":null},{"value":0,"type":null},{"value":0,"type":null},{"value":0,"type":null}],[{"value":0,"type":null},{"value":0,"type":null},{"value":0,"type":null},{"value":0,"type":null},{"value":0,"type":null},{"value":0,"type":null},{"value":0,"type":null},{"value":0,"type":null},{"value":0,"type":null},{"value":0,"type":null},{"value":0,"type":null},{"value":0,"type":null},{"value":0,"type":null},{"value":0,"type":null},{"value":0,"type":null},{"value":0,"type":null},{"value":0,"type":null},{"value":0,"type":null},{"value":0,"type":null},{"value":0,"type":null},{"value":0,"type":null},{"value":0,"type":null},{"value":0,"type":null},{"value":0,"type":null},{"value":0,"type":null},{"value":0,"type":null},{"value":0,"type":null},{"value":0,"type":null},{"value":0,"type":null},{"value":0,"type":null},{"value":0,"type":null},{"value":0,"type":null},{"value":0,"type":null}],[{"value":0,"type":null},{"value":0,"type":null},{"value":0,"type":null},{"value":0,"type":null},{"value":0,"type":null},{"value":0,"type":null},{"value":0,"type":null},{"value":0,"type":null},{"value":0,"type":null},{"value":0,"type":null},{"value":0,"type":null},{"value":0,"type":null},{"value":0,"type":null},{"value":0,"type":null},{"value":0,"type":null},{"value":0,"type":null},{"value":0,"type":null},{"value":0,"type":null},{"value":0,"type":null},{"value":0,"type":null},{"value":0,"type":null},{"value":0,"type":null},{"value":0,"type":null},{"value":0,"type":null},{"value":0,"type":null},{"value":0,"type":null},{"value":0,"type":null},{"value":0,"type":null},{"value":0,"type":null},{"value":0,"type":null},{"value":0,"type":null},{"value":0,"type":null},{"value":0,"type":null}],[{"value":0,"type":null},{"value":0,"type":null},{"value":0,"type":null},{"value":0,"type":null},{"value":0,"type":null},{"value":0,"type":null},{"value":0,"type":null},{"value":0,"type":null},{"value":0,"type":null},{"value":0,"type":null},{"value":0,"type":null},{"value":0,"type":null},{"value":0,"type":null},{"value":0,"type":null},{"value":0,"type":null},{"value":0,"type":null},{"value":0,"type":null},{"value":0,"type":null},{"value":0,"type":null},{"value":0,"type":null},{"value":0,"type":null},{"value":0,"type":null},{"value":0,"type":null},{"value":0,"type":null},{"value":0,"type":null},{"value":0,"type":null},{"value":0,"type":null},{"value":0,"type":null},{"value":0,"type":null},{"value":0,"type":null},{"value":0,"type":null},{"value":0,"type":null},{"value":0,"type":null}],[{"value":0,"type":null},{"value":0,"type":null},{"value":0,"type":null},{"value":0,"type":null},{"value":0,"type":null},{"value":0,"type":null},{"value":0,"type":null},{"value":0,"type":null},{"value":0,"type":null},{"value":0,"type":null},{"value":0,"type":null},{"value":0,"type":null},{"value":0,"type":null},{"value":0,"type":null},{"value":0,"type":null},{"value":0,"type":null},{"value":0,"type":null},{"value":0,"type":null},{"value":0,"type":null},{"value":0,"type":null},{"value":0,"type":null},{"value":0,"type":null},{"value":0,"type":null},{"value":0,"type":null},{"value":0,"type":null},{"value":0,"type":null},{"value":0,"type":null},{"value":0,"type":null},{"value":0,"type":null},{"value":0,"type":null},{"value":0,"type":null},{"value":0,"type":null},{"value":0,"type":null}],[{"value":0,"type":null},{"value":0,"type":null},{"value":0,"type":null},{"value":0,"type":null},{"value":0,"type":null},{"value":0,"type":null},{"value":0,"type":null},{"value":0,"type":null},{"value":0,"type":null},{"value":0,"type":null},{"value":0,"type":null},{"value":0,"type":null},{"value":0,"type":null},{"value":0,"type":null},{"value":0,"type":null},{"value":0,"type":null},{"value":0,"type":null},{"value":0,"type":null},{"value":0,"type":null},{"value":0,"type":null},{"value":0,"type":null},{"value":0,"type":null},{"value":0,"type":null},{"value":0,"type":null},{"value":0,"type":null},{"value":0,"type":null},{"value":0,"type":null},{"value":0,"type":null},{"value":0,"type":null},{"value":0,"type":null},{"value":0,"type":null},{"value":0,"type":null},{"value":0,"type":null}],[{"value":0,"type":null},{"value":0,"type":null},{"value":0,"type":null},{"value":0,"type":null},{"value":0,"type":null},{"value":0,"type":null},{"value":0,"type":null},{"value":0,"type":null},{"value":0,"type":null},{"value":0,"type":null},{"value":0,"type":null},{"value":0,"type":null},{"value":0,"type":null},{"value":0,"type":null},{"value":0,"type":null},{"value":0,"type":null},{"value":0,"type":null},{"value":0,"type":null},{"value":0,"type":null},{"value":0,"type":null},{"value":0,"type":null},{"value":0,"type":null},{"value":0,"type":null},{"value":0,"type":null},{"value":0,"type":null},{"value":0,"type":null},{"value":0,"type":null},{"value":0,"type":null},{"value":0,"type":null},{"value":0,"type":null},{"value":0,"type":null},{"value":0,"type":null},{"value":0,"type":null}],[{"value":0,"type":null},{"value":0,"type":null},{"value":0,"type":null},{"value":0,"type":null},{"value":0,"type":null},{"value":0,"type":null},{"value":0,"type":null},{"value":0,"type":null},{"value":0,"type":null},{"value":0,"type":null},{"value":0,"type":null},{"value":0,"type":null},{"value":0,"type":null},{"value":0,"type":null},{"value":0,"type":null},{"value":0,"type":null},{"value":0,"type":null},{"value":0,"type":null},{"value":0,"type":null},{"value":0,"type":null},{"value":0,"type":null},{"value":0,"type":null},{"value":0,"type":null},{"value":0,"type":null},{"value":0,"type":null},{"value":0,"type":null},{"value":0,"type":null},{"value":0,"type":null},{"value":0,"type":null},{"value":0,"type":null},{"value":0,"type":null},{"value":0,"type":null},{"value":0,"type":null}],[{"value":0,"type":null},{"value":0,"type":null},{"value":0,"type":null},{"value":0,"type":null},{"value":0,"type":null},{"value":0,"type":null},{"value":0,"type":null},{"value":0,"type":null},{"value":0,"type":null},{"value":0,"type":null},{"value":0,"type":null},{"value":0,"type":null},{"value":0,"type":null},{"value":0,"type":null},{"value":0,"type":null},{"value":0,"type":null},{"value":0,"type":null},{"value":0,"type":null},{"value":0,"type":null},{"value":0,"type":null},{"value":0,"type":null},{"value":0,"type":null},{"value":0,"type":null},{"value":0,"type":null},{"value":0,"type":null},{"value":0,"type":null},{"value":0,"type":null},{"value":0,"type":null},{"value":0,"type":null},{"value":0,"type":null},{"value":0,"type":null},{"value":0,"type":null},{"value":0,"type":null}],[{"value":0,"type":null},{"value":0,"type":null},{"value":0,"type":null},{"value":0,"type":null},{"value":0,"type":null},{"value":0,"type":null},{"value":0,"type":null},{"value":0,"type":null},{"value":0,"type":null},{"value":0,"type":null},{"value":0,"type":null},{"value":0,"type":null},{"value":0,"type":null},{"value":0,"type":null},{"value":0,"type":null},{"value":0,"type":null},{"value":0,"type":null},{"value":0,"type":null},{"value":0,"type":null},{"value":0,"type":null},{"value":0,"type":null},{"value":0,"type":null},{"value":0,"type":null},{"value":0,"type":null},{"value":0,"type":null},{"value":0,"type":null},{"value":0,"type":null},{"value":0,"type":null},{"value":0,"type":null},{"value":0,"type":null},{"value":0,"type":null},{"value":0,"type":null},{"value":0,"type":null}],[{"value":0,"type":null},{"value":0,"type":null},{"value":0,"type":null},{"value":0,"type":null},{"value":0,"type":null},{"value":0,"type":null},{"value":0,"type":null},{"value":0,"type":null},{"value":0,"type":null},{"value":0,"type":null},{"value":0,"type":null},{"value":0,"type":null},{"value":0,"type":null},{"value":0,"type":null},{"value":0,"type":null},{"value":0,"type":null},{"value":0,"type":null},{"value":0,"type":null},{"value":0,"type":null},{"value":0,"type":null},{"value":0,"type":null},{"value":0,"type":null},{"value":0,"type":null},{"value":0,"type":null},{"value":0,"type":null},{"value":0,"type":null},{"value":0,"type":null},{"value":0,"type":null},{"value":0,"type":null},{"value":0,"type":null},{"value":0,"type":null},{"value":0,"type":null},{"value":0,"type":null}],[{"value":0,"type":null},{"value":0,"type":null},{"value":0,"type":null},{"value":0,"type":null},{"value":0,"type":null},{"value":0,"type":null},{"value":0,"type":null},{"value":0,"type":null},{"value":0,"type":null},{"value":0,"type":null},{"value":0,"type":null},{"value":0,"type":null},{"value":0,"type":null},{"value":0,"type":null},{"value":0,"type":null},{"value":0,"type":null},{"value":0,"type":null},{"value":0,"type":null},{"value":0,"type":null},{"value":0,"type":null},{"value":0,"type":null},{"value":0,"type":null},{"value":0,"type":null},{"value":0,"type":null},{"value":0,"type":null},{"value":0,"type":null},{"value":0,"type":null},{"value":0,"type":null},{"value":0,"type":null},{"value":0,"type":null},{"value":0,"type":null},{"value":0,"type":null},{"value":0,"type":null}],[{"value":0,"type":null},{"value":0,"type":null},{"value":0,"type":null},{"value":0,"type":null},{"value":0,"type":null},{"value":0,"type":null},{"value":0,"type":null},{"value":0,"type":null},{"value":0,"type":null},{"value":0,"type":null},{"value":0,"type":null},{"value":0,"type":null},{"value":0,"type":null},{"value":0,"type":null},{"value":0,"type":null},{"value":0,"type":null},{"value":0,"type":null},{"value":0,"type":null},{"value":0,"type":null},{"value":0,"type":null},{"value":0,"type":null},{"value":0,"type":null},{"value":0,"type":null},{"value":0,"type":null},{"value":0,"type":null},{"value":0,"type":null},{"value":0,"type":null},{"value":0,"type":null},{"value":0,"type":null},{"value":0,"type":null},{"value":0,"type":null},{"value":0,"type":null},{"value":0,"type":null}],[{"value":0,"type":null},{"value":0,"type":null},{"value":0,"type":null},{"value":0,"type":null},{"value":0,"type":null},{"value":0,"type":null},{"value":0,"type":null},{"value":0,"type":null},{"value":0,"type":null},{"value":0,"type":null},{"value":0,"type":null},{"value":0,"type":null},{"value":0,"type":null},{"value":0,"type":null},{"value":0,"type":null},{"value":0,"type":null},{"value":0,"type":null},{"value":0,"type":null},{"value":0,"type":null},{"value":0,"type":null},{"value":0,"type":null},{"value":0,"type":null},{"value":0,"type":null},{"value":0,"type":null},{"value":0,"type":null},{"value":0,"type":null},{"value":0,"type":null},{"value":0,"type":null},{"value":0,"type":null},{"value":0,"type":null},{"value":0,"type":null},{"value":0,"type":null},{"value":0,"type":null}],[{"value":0,"type":null},{"value":0,"type":null},{"value":0,"type":null},{"value":0,"type":null},{"value":0,"type":null},{"value":0,"type":null},{"value":0,"type":null},{"value":0,"type":null},{"value":0,"type":null},{"value":0,"type":null},{"value":0,"type":null},{"value":0,"type":null},{"value":0,"type":null},{"value":0,"type":null},{"value":0,"type":null},{"value":0,"type":null},{"value":0,"type":null},{"value":0,"type":null},{"value":0,"type":null},{"value":0,"type":null},{"value":0,"type":null},{"value":0,"type":null},{"value":0,"type":null},{"value":0,"type":null},{"value":0,"type":null},{"value":0,"type":null},{"value":0,"type":null},{"value":0,"type":null},{"value":0,"type":null},{"value":0,"type":null},{"value":0,"type":null},{"value":0,"type":null},{"value":0,"type":null}]]]},"powerUps":[{"value":1,"chunkNum":0,"xTile":1,"yTile":0},{"value":1,"chunkNum":0,"xTile":2,"yTile":0},{"value":1,"chunkNum":0,"xTile":0,"yTile":1},{"value":1,"chunkNum":0,"xTile":3,"yTile":1},{"value":2,"chunkNum":0,"xTile":11,"yTile":1},{"value":2,"chunkNum":0,"xTile":10,"yTile":2},{"value":2,"chunkNum":0,"xTile":12,"yTile":2},{"value":3,"chunkNum":0,"xTile":6,"yTile":4},{"value":4,"chunkNum":0,"xTile":9,"yTile":6},{"value":2,"chunkNum":0,"xTile":0,"yTile":7},{"value":2,"chunkNum":0,"xTile":1,"yTile":7}],"enemies":[{"value":1,"chunkIdx":0,"xTile":6,"yTile":0,"lb":{"chunkIdx":0,"tileIdx":0},"rb":{"chunkIdx":0,"tileIdx":10}},{"value":1,"chunkIdx":0,"xTile":13,"yTile":5,"lb":{"chunkIdx":0,"tileIdx":9},"rb":{"chunkIdx":0,"tileIdx":15}},{"value":1,"chunkIdx":0,"xTile":6,"yTile":6,"lb":{"chunkIdx":0,"tileIdx":0},"rb":{"chunkIdx":0,"tileIdx":13}}]}